HISTORY
MANIFEST
MANIFEST.in
README
README.rst
requirements.dev.txt
run-tests
setup.cfg
setup.py
./src/connection.c
./src/constants.c
./src/exceptions.c
./src/fields.c
./src/format.c
./src/module.c
./src/results.c
doc/Makefile
doc/conf.py
doc/index.rst
doc/modules.rst
doc/wsql.cluster.rst
doc/wsql.rst
doc/_build/.buildinfo
doc/_build/genindex.html
doc/_build/index.html
doc/_build/modules.html
doc/_build/objects.inv
doc/_build/py-modindex.html
doc/_build/search.html
doc/_build/searchindex.js
doc/_build/wsql.cluster.html
doc/_build/wsql.html
doc/_build/.doctrees/environment.pickle
doc/_build/.doctrees/index.doctree
doc/_build/.doctrees/modules.doctree
doc/_build/.doctrees/wsql.cluster.doctree
doc/_build/.doctrees/wsql.doctree
doc/_build/_sources/index.txt
doc/_build/_sources/modules.txt
doc/_build/_sources/wsql.cluster.txt
doc/_build/_sources/wsql.txt
doc/_build/_static/ajax-loader.gif
doc/_build/_static/alabaster.css
doc/_build/_static/basic.css
doc/_build/_static/comment-bright.png
doc/_build/_static/comment-close.png
doc/_build/_static/comment.png
doc/_build/_static/doctools.js
doc/_build/_static/down-pressed.png
doc/_build/_static/down.png
doc/_build/_static/file.png
doc/_build/_static/jquery-1.11.1.js
doc/_build/_static/jquery.js
doc/_build/_static/minus.png
doc/_build/_static/plus.png
doc/_build/_static/pygments.css
doc/_build/_static/searchtools.js
doc/_build/_static/underscore-1.3.1.js
doc/_build/_static/underscore.js
doc/_build/_static/up-pressed.png
doc/_build/_static/up.png
doc/_build/_static/websupport.js
extra/websqlclient/.git
extra/websqlclient/.gitignore
extra/websqlclient/CMakeLists.txt
extra/websqlclient/CPackConfig.cmake
extra/websqlclient/CPackSourceConfig.cmake
extra/websqlclient/LICENSE
extra/websqlclient/Makefile
extra/websqlclient/README
extra/websqlclient/VERSION
extra/websqlclient/VERSION.dep
extra/websqlclient/VERSION.server
extra/websqlclient/config.h.cmake
extra/websqlclient/configure.cmake
extra/websqlclient/info_macros.cmake
wsql.egg-info/PKG-INFO
wsql.egg-info/SOURCES.txt
wsql.egg-info/dependency_links.txt
wsql.egg-info/pbr.json
wsql.egg-info/top_level.txt
