Metadata-Version: 1.1
Name: wsql
Version: 1.2.12
Summary: Asynchronous Python interface to MySQL
Home-page: https://github.com/WSQL/wsql
Author: Bulat Gaifullin
Author-email: gaifullinbf@gmail.com
License: GPL
Download-URL: https://github.com/WebSQL/wsql/archive/v1.2.12.tar.gz
Keywords: mysql,asyncio,asyncsql
Platform: UNKNOWN
Classifier: Development Status :: 5 - Production/Stable
Classifier: Environment :: Other Environment
Classifier: License :: OSI Approved :: GNU General Public License (GPL)
Classifier: Operating System :: MacOS :: MacOS X
Classifier: Operating System :: OS Independent
Classifier: Operating System :: POSIX
Classifier: Operating System :: POSIX :: Linux
Classifier: Operating System :: Unix
Classifier: Programming Language :: C
Classifier: Programming Language :: Python :: 3.4
Classifier: Topic :: Database
Classifier: Topic :: Database :: Database Engines/Servers
